hpo_similarity/__init__.py
hpo_similarity/__main__.py
hpo_similarity/analyse_genes.py
hpo_similarity/check_proband_terms.py
hpo_similarity/get_scores.py
hpo_similarity/load_files.py
hpo_similarity/obo.py
hpo_similarity/ontology.py
hpo_similarity/permute_probands.py
hpo_similarity/similarity.py
hpo_similarity/test_similarity.py
hpo_similarity/data/hp.obo
hpo_similarity-0.5.0.dist-info/METADATA
hpo_similarity-0.5.0.dist-info/RECORD
hpo_similarity-0.5.0.dist-info/WHEEL
hpo_similarity-0.5.0.dist-info/entry_points.txt
hpo_similarity-0.5.0.dist-info/top_level.txt
