Metadata-Version: 2.1
Name: hpo-similarity
Version: 0.5.0
Summary: Testing similarity of HPO terms between probands sharing         variants in genes.
Home-page: UNKNOWN
Author: Jeremy McRae
Author-email: jeremy.mcrae@sanger.ac.uk
License: MIT
Platform: UNKNOWN
Classifier: Development Status :: 3 - Alpha
Classifier: License :: OSI Approved :: MIT License
Requires-Dist: networkx (>=1.8.1)
